arpegio/__init__.py
arpegio/blog/__init__.py
arpegio/blog/apps.py
arpegio/blog/managers.py
arpegio/blog/models.py
arpegio/blog/urls.py
arpegio/blog/views.py
arpegio/blog/migrations/__init__.py
arpegio/blog/templates/arpegio-blog/post_detail.html
arpegio/blog/templates/arpegio-blog/post_list.html
arpegio/blog/templatetags/__init__.py
arpegio/blog/templatetags/arpegio_blog_tags.py
arpegio/categories/__init__.py
arpegio/categories/apps.py
arpegio/categories/models.py
arpegio/categories/urls.py
arpegio/categories/views.py
arpegio/categories/migrations/__init__.py
arpegio/core/__init__.py
arpegio/core/apps.py
arpegio/core/context_processors.py
arpegio/core/models.py
arpegio/core/settings/__init__.py
arpegio/core/settings/sites.py
arpegio/core/templates/arpegio-core/base.html
arpegio/core/templates/arpegio-core/footer.html
arpegio/core/templates/arpegio-core/head.html
arpegio/core/templates/arpegio-core/header.html
arpegio/core/templates/arpegio-core/menu.html
arpegio/core/templates/arpegio-core/scripts.html
arpegio/core/templatetags/__init__.py
arpegio/core/templatetags/arpegio_tags.py
arpegio/pages/__init__.py
arpegio/pages/apps.py
arpegio/pages/models.py
arpegio/pages/urls.py
arpegio/pages/views.py
arpegio/pages/migrations/__init__.py
arpegio/pages/templates/arpegio-pages/page_detail.html
arpegio/tags/__init__.py
arpegio/tags/apps.py
arpegio/tags/models.py
arpegio/tags/urls.py
arpegio/tags/views.py
arpegio/tags/migrations/__init__.py
arpegio-0.3.4.dist-info/DESCRIPTION.rst
arpegio-0.3.4.dist-info/METADATA
arpegio-0.3.4.dist-info/RECORD
arpegio-0.3.4.dist-info/WHEEL
arpegio-0.3.4.dist-info/metadata.json
arpegio-0.3.4.dist-info/top_level.txt
